{
  "project_info": {
    "project_number": "814686791102",
    "firebase_url": "https://selfjournal-cfedc.firebaseio.com",
    "project_id": "selfjournal-cfedc",
    "storage_bucket": "selfjournal-cfedc.appspot.com"
  },
  "client": [
    {
      "client_info": {
        "mobilesdk_app_id": "1:814686791102:android:891a43d4271e3d86f185ef",
        "android_client_info": {
          "package_name": "com.example.selfjournal"
        }
      },
      "oauth_client": [
        {
          "client_id": "814686791102-ifna8gdrogj6u9rfss99iu2buf1eca07.apps.googleusercontent.com",
          "client_type": 3
        }
      ],
      "api_key": [
        {
          "current_key": "AIzaSyBHnWIbyuKtEiB9q5Ca1KZ5Olc9NOdxqU4"
        }
      ],
      "services": {
        "appinvite_service": {
          "other_platform_oauth_client": [
            {
              "client_id": "814686791102-ifna8gdrogj6u9rfss99iu2buf1eca07.apps.googleusercontent.com",
              "client_type": 3
            }
          ]
        }
      }
    }
  ],
  "configuration_version": "1"
}